retbrown_cdk_ecr_deployment/__init__.py
retbrown_cdk_ecr_deployment/py.typed
retbrown_cdk_ecr_deployment/_jsii/__init__.py
retbrown_cdk_ecr_deployment/_jsii/retbrown-cdk-ecr-deployment@1.0.3.jsii.tgz
retbrown_cdk_ecr_deployment-1.0.3.dist-info/LICENSE
retbrown_cdk_ecr_deployment-1.0.3.dist-info/METADATA
retbrown_cdk_ecr_deployment-1.0.3.dist-info/NOTICE
retbrown_cdk_ecr_deployment-1.0.3.dist-info/WHEEL
retbrown_cdk_ecr_deployment-1.0.3.dist-info/top_level.txt
retbrown_cdk_ecr_deployment-1.0.3.dist-info/RECORD
