Metadata-Version: 2.1
Name: retbrown-cdk-ecr-deployment
Version: 1.0.3
Summary: CDK construct to deploy docker image to Amazon ECR
Home-page: https://github.com/retbrown/retbrown-cdk-ecr-deployment
Author: retbrown
License: Apache-2.0
Project-URL: Source, https://github.com/retbrown/retbrown-cdk-ecr-deployment
Platform: UNKNOWN
Classifier: Intended Audience :: Developers
Classifier: Operating System :: OS Independent
Classifier: Programming Language :: JavaScript
Classifier: Programming Language :: Python :: 3 :: Only
Classifier: Programming Language :: Python :: 3.6
Classifier: Programming Language :: Python :: 3.7
Classifier: Programming Language :: Python :: 3.8
Classifier: Programming Language :: Python :: 3.9
Classifier: Typing :: Typed
Classifier: Development Status :: 5 - Production/Stable
Classifier: License :: OSI Approved
Requires-Python: >=3.6
License-File: LICENSE
License-File: NOTICE
Requires-Dist: aws-cdk.aws-ec2 (<2.0.0,>=1.135.0)
Requires-Dist: aws-cdk.aws-iam (<2.0.0,>=1.135.0)
Requires-Dist: aws-cdk.aws-lambda (<2.0.0,>=1.135.0)
Requires-Dist: aws-cdk.core (<2.0.0,>=1.135.0)
Requires-Dist: constructs (<4.0.0,>=3.2.27)
Requires-Dist: jsii (<2.0.0,>=1.49.0)
Requires-Dist: publication (>=0.0.3)
